division.v
module division (
    input [31:0]a,
    input [31:0]b,
    output [31:0]res
);

wire a_sign;
wire b_sign;
wire [7:0] a_exponent;
wire [7:0]b_exponent;
wire [23:0]a_mantissa;
wire [23:0]b_mantissa;

reg [23:0] aligned_a;
reg [23:0] aligned_b;
reg [7:0] aligned_expo;

assign a_sign = a[31];
assign b_sign = b[31];
assign a_exponent = a[30:23];
assign b_exponent = b[30:23];
assign a_mantissa = {1'b1,a[22:0]};
assign b_mantissa = {1'b1,b[22:0]};

reg [47:0] n_mul;
reg n_sign;
reg [7:0] n_exp;

normal_div nd1(n_mul,n_exp,n_sign,res);

always @(*) begin
    n_sign=a_sign^b_sign;
    n_exp=a_exponent-b_exponent+8'd127;
    n_mul=a_mantissa/b_mantissa;
end

endmodule

module normal_div(
    input [47:0] mantissa,
    input [7:0] exponent,
    input sign,
    output [31:0] out
  );
  
  assign out[31]=sign;
  assign out[30:23]=o_e+1;
  assign out[22:0]=o_m[46:24];
  reg [7:0]o_e;
  reg [47:0]o_m;
  integer i;
  
  always @ (*) begin
    o_e=exponent;
    o_m=mantissa;
  
    for (int i=47; i>0; i=i-1) begin
      if (o_m[47]==0) begin
        o_e=o_e-1;
        o_m=o_m<<1;
      end
      else begin
        o_e=o_e;
        o_m=o_m;
      end
    end
  end
  endmodule

multiplication.v
module multiplication (
    input [31:0]a,
    input [31:0]b,
    output [31:0]res
);

wire a_sign;
wire b_sign;
wire [7:0] a_exponent;
wire [7:0]b_exponent;
wire [23:0]a_mantissa;
wire [23:0]b_mantissa;

reg [23:0] aligned_a;
reg [23:0] aligned_b;
reg [7:0] aligned_expo;

assign a_sign = a[31];
assign b_sign = b[31];
assign a_exponent = a[30:23];
assign b_exponent = b[30:23];
assign a_mantissa = {1'b1,a[22:0]};
assign b_mantissa = {1'b1,b[22:0]};

reg [47:0] n_mul;
reg n_sign;
reg [7:0] n_exp;

normal_mul m1(n_mul,n_exp,n_sign,res);

always @(*) begin
    n_sign=a_sign^b_sign;
    n_exp=a_exponent+b_exponent-8'd127;
    n_mul=a_mantissa*b_mantissa;
end

endmodule

module normal_mul(
    input [47:0] mantissa,
    input [7:0] exponent,
    input sign,
    output [31:0] out
  );
  
  assign out[31]=sign;
  assign out[30:23]=o_e+1;
  assign out[22:0]=o_m[46:24];
  reg [7:0]o_e;
  reg [47:0]o_m;
  integer i;
  
  always @ (*) begin
    o_e=exponent;
    o_m=mantissa;
  
    for (int i=47; i>0; i=i-1) begin
      if (o_m[47]==0) begin
        o_e=o_e-1;
        o_m=o_m<<1;
      end
      else begin
        o_e=o_e;
        o_m=o_m;
      end
    end
  end
  endmodule

adder.v
module adder(
    input [31:0] a,
    input [31:0] b,
    output [31:0] sum
);

wire a_sign;
wire b_sign;
wire [7:0] a_exponent;
wire [7:0]b_exponent;
wire [23:0]a_mantissa;
wire [23:0]b_mantissa;

reg [23:0] aligned_a;
reg [23:0] aligned_b;
reg [7:0] aligned_expo;

assign a_sign = a[31];
assign b_sign = b[31];
assign a_exponent = a[30:23];
assign b_exponent = b[30:23];
assign a_mantissa = {1'b1,a[22:0]};
assign b_mantissa = {1'b1,b[22:0]};

reg [24:0] n_sum;
reg n_sign;
reg [7:0] n_exp;


normal_add normalization(n_sum,n_exp,n_sign,sum);

always @(*) begin

    if (a_exponent > b_exponent) begin        // A is bigger than B

      aligned_expo = a_exponent - b_exponent;
      aligned_b = b_mantissa >> aligned_expo;
      aligned_a = a_mantissa;
      n_sign=a_sign;
      n_exp=a_exponent;

      if (a_sign==b_sign) begin             
        n_sum=aligned_a+aligned_b;

      end
      else begin
        n_sum=aligned_a-aligned_b;
      end
    end
    
    else if (b_exponent > a_exponent) begin      // B is bigger than A

      aligned_expo = b_exponent - a_exponent;
      aligned_a = a_mantissa >> aligned_expo;
      aligned_b = b_mantissa;
      n_sign=b_sign;
      n_exp=b_exponent;

      if (a_sign==b_sign) begin
        n_sum=aligned_a+aligned_b;
      end
      else begin
        n_sum=aligned_b-aligned_a;
      end

    end
    
    else begin                             // A & B are same
      aligned_expo = 8'd0;
      aligned_a = a_mantissa;
      aligned_b = b_mantissa;
      n_exp=a_exponent;

      if(a_sign==b_sign) begin
        n_sum=a_mantissa+b_mantissa;
        n_sign=a_sign;
      end

      else begin
        if (a_mantissa>b_mantissa) begin
          n_sum=aligned_a-aligned_b;
          n_sign=a_sign;
        end
        else if(a_mantissa<b_mantissa)begin
          n_sum=aligned_b-aligned_a;
          n_sign=b_sign;
        end
        else begin
          n_sum=25'b1_00000000_00000000_00000000;
          n_sign=0;
          n_exp=-1;
        end
      end
    end
  end

endmodule

module normal_add(
  input [24:0] mantissa,
  input [7:0] exponent,
  input sign,
  output [31:0] out
);

assign out[31]=sign;
assign out[30:23]=o_e+1;
assign out[22:0]=o_m[23:1];
reg [7:0]o_e;
reg [24:0]o_m;
integer i;

always @ (*) begin
  o_e=exponent;
  o_m=mantissa;

  for (int i=24; i>1; i=i-1) begin
    if (o_m[24]==0) begin
      o_e=o_e-1;
      o_m=o_m<<1;
    end
    else begin
      o_e=o_e;
      o_m=o_m;
      // $display("[else] i=%d mantisaa=%b exp=%b sign=%b",i,o_m,o_e,sign);
    end
  end
end
endmodule

fpu.v
`include "adder.v"
`include "multiplication.v"
`include "division.v"

`define ADD 2'b00
`define SUB 2'b01
`define MUL 2'b10
`define DIV 2'b11

module fpu(
    input [31:0] A,
    input [31:0] B,
    input [1:0] opcode,
    input clk,
    output reg [31:0] OUT
);

reg [31:0]add_result;
reg [31:0]sub_result;
reg [31:0]mul_result;
reg [31:0]div_result;


adder a1(
    .a(A),
    .b(B),
    .sum(add_result)
);

adder a2(
    .a(A),
    .b({~B[31],B[30:0]}),
    .sum(sub_result)
);

multiplication m1(
    .a(A),
    .b(B),
    .res(mul_result)
);

division d1(
    .a(A),
    .b(B),
    .res(div_result)
);

always @(posedge clk) begin
    case (opcode)
        `ADD: begin
            OUT<=add_result;
        end
        `SUB: begin
            OUT<=sub_result;
        end
        `MUL: begin
            OUT<=mul_result;
        end
        `DIV: begin
            OUT<=div_result;
        end
        default: begin
            OUT<=32'd0;
        end
    endcase
end

endmodule

tb.v
`include "fpu.v"

module top;

    reg [31:0]a;
    reg [31:0]b;
    reg clk=0;
    reg [1:0]opcode;
    wire [31:0]out;
    reg [22:0] sum1;
    reg [46:0]n_mul;

    fpu dut(a,b,opcode,clk,out);

    initial forever #1 clk=~clk;

    initial begin
        a=32'h3f800000;
        b=32'h40000000;
        @(negedge clk);
        opcode=`ADD;
        @(posedge clk);
        $display("a=%h   b=%h  a+b=%h",a,b,out);

        @(negedge clk);
        opcode=`SUB;
        @(posedge clk);
        $display("a=%h   b=%h  a-b=%h",a,b,out);

        @(negedge clk);
        opcode=`MUL;
        @(posedge clk);
        $display("a=%h   b=%h  a*b=%h",a,b,out);

        @(negedge clk);
        opcode=`DIV;
        @(posedge clk);
        $display("a=%h   b=%h  a/b=%h",a,b,out);
        @(posedge clk);
        $finish;


    end

    initial begin
        $dumpfile("wave.vcd");
        $dumpvars();

    end
endmodule

wave.vcd
$date
	Sun Sep 03 15:07:50 2023
$end
$version
	Icarus Verilog
$end
$timescale
	1s
$end
$scope module top $end
$var wire 32 ! out [31:0] $end
$var reg 32 " a [31:0] $end
$var reg 32 # b [31:0] $end
$var reg 1 $ clk $end
$var reg 2 % opcode [1:0] $end
$scope module dut $end
$var wire 32 & A [31:0] $end
$var wire 32 ' B [31:0] $end
$var wire 1 $ clk $end
$var wire 2 ( opcode [1:0] $end
$var wire 32 ) sub_result [31:0] $end
$var wire 32 * mul_result [31:0] $end
$var wire 32 + div_result [31:0] $end
$var wire 32 , add_result [31:0] $end
$var reg 32 - OUT [31:0] $end
$scope module a1 $end
$var wire 32 . a [31:0] $end
$var wire 32 / b [31:0] $end
$var wire 32 0 sum [31:0] $end
$var wire 1 1 b_sign $end
$var wire 24 2 b_mantissa [23:0] $end
$var wire 8 3 b_exponent [7:0] $end
$var wire 1 4 a_sign $end
$var wire 24 5 a_mantissa [23:0] $end
$var wire 8 6 a_exponent [7:0] $end
$var reg 24 7 aligned_a [23:0] $end
$var reg 24 8 aligned_b [23:0] $end
$var reg 8 9 aligned_expo [7:0] $end
$var reg 8 : n_exp [7:0] $end
$var reg 1 ; n_sign $end
$var reg 25 < n_sum [24:0] $end
$scope module normalization $end
$var wire 8 = exponent [7:0] $end
$var wire 25 > mantissa [24:0] $end
$var wire 1 ; sign $end
$var wire 32 ? out [31:0] $end
$var reg 8 @ o_e [7:0] $end
$var reg 25 A o_m [24:0] $end
$scope begin $ivl_for_loop0 $end
$var integer 32 B i [31:0] $end
$upscope $end
$upscope $end
$upscope $end
$scope module a2 $end
$var wire 32 C a [31:0] $end
$var wire 32 D b [31:0] $end
$var wire 32 E sum [31:0] $end
$var wire 1 F b_sign $end
$var wire 24 G b_mantissa [23:0] $end
$var wire 8 H b_exponent [7:0] $end
$var wire 1 I a_sign $end
$var wire 24 J a_mantissa [23:0] $end
$var wire 8 K a_exponent [7:0] $end
$var reg 24 L aligned_a [23:0] $end
$var reg 24 M aligned_b [23:0] $end
$var reg 8 N aligned_expo [7:0] $end
$var reg 8 O n_exp [7:0] $end
$var reg 1 P n_sign $end
$var reg 25 Q n_sum [24:0] $end
$scope module normalization $end
$var wire 8 R exponent [7:0] $end
$var wire 25 S mantissa [24:0] $end
$var wire 1 P sign $end
$var wire 32 T out [31:0] $end
$var reg 8 U o_e [7:0] $end
$var reg 25 V o_m [24:0] $end
$scope begin $ivl_for_loop0 $end
$var integer 32 W i [31:0] $end
$upscope $end
$upscope $end
$upscope $end
$scope module d1 $end
$var wire 32 X a [31:0] $end
$var wire 32 Y b [31:0] $end
$var wire 32 Z res [31:0] $end
$var wire 1 [ b_sign $end
$var wire 24 \ b_mantissa [23:0] $end
$var wire 8 ] b_exponent [7:0] $end
$var wire 1 ^ a_sign $end
$var wire 24 _ a_mantissa [23:0] $end
$var wire 8 ` a_exponent [7:0] $end
$var reg 8 a n_exp [7:0] $end
$var reg 48 b n_mul [47:0] $end
$var reg 1 c n_sign $end
$scope module nd1 $end
$var wire 8 d exponent [7:0] $end
$var wire 48 e mantissa [47:0] $end
$var wire 1 c sign $end
$var wire 32 f out [31:0] $end
$var reg 8 g o_e [7:0] $end
$var reg 48 h o_m [47:0] $end
$scope begin $ivl_for_loop2 $end
$var integer 32 i i [31:0] $end
$upscope $end
$upscope $end
$upscope $end
$scope module m1 $end
$var wire 32 j a [31:0] $end
$var wire 32 k b [31:0] $end
$var wire 32 l res [31:0] $end
$var wire 1 m b_sign $end
$var wire 24 n b_mantissa [23:0] $end
$var wire 8 o b_exponent [7:0] $end
$var wire 1 p a_sign $end
$var wire 24 q a_mantissa [23:0] $end
$var wire 8 r a_exponent [7:0] $end
$var reg 8 s n_exp [7:0] $end
$var reg 48 t n_mul [47:0] $end
$var reg 1 u n_sign $end
$scope module m1 $end
$var wire 8 v exponent [7:0] $end
$var wire 48 w mantissa [47:0] $end
$var wire 1 u sign $end
$var wire 32 x out [31:0] $end
$var reg 8 y o_e [7:0] $end
$var reg 48 z o_m [47:0] $end
$scope begin $ivl_for_loop1 $end
$var integer 32 { i [31:0] $end
$upscope $end
$upscope $end
$upscope $end
$upscope $end
$upscope $end
$enddefinitions $end
$comment Show the parameter values. $end
$dumpall
$end
#0
$dumpvars
b0 {
b100000000000000000000000000000000000000000000000 z
b1111111 y
b1000000000000000000000000000000 x
b10000000000000000000000000000000000000000000000 w
b10000000 v
0u
b10000000000000000000000000000000000000000000000 t
b10000000 s
b1111111 r
b100000000000000000000000 q
0p
b10000000 o
b100000000000000000000000 n
0m
b1000000000000000000000000000000 l
b1000000000000000000000000000000 k
b111111100000000000000000000000 j
b0 i
b100000000000000000000000000000000000000000000000 h
b1001111 g
b101000000000000000000000000000 f
b1 e
b1111110 d
0c
b1 b
b1111110 a
b1111111 `
b100000000000000000000000 _
0^
b10000000 ]
b100000000000000000000000 \
0[
b101000000000000000000000000000 Z
b1000000000000000000000000000000 Y
b111111100000000000000000000000 X
b1 W
b1000000000000000000000000 V
b1111110 U
b10111111100000000000000000000000 T
b10000000000000000000000 S
b10000000 R
b10000000000000000000000 Q
1P
b10000000 O
b1 N
b100000000000000000000000 M
b10000000000000000000000 L
b1111111 K
b100000000000000000000000 J
0I
b10000000 H
b100000000000000000000000 G
1F
b10111111100000000000000000000000 E
b11000000000000000000000000000000 D
b111111100000000000000000000000 C
b1 B
b1100000000000000000000000 A
b1111111 @
b1000000010000000000000000000000 ?
b110000000000000000000000 >
b10000000 =
b110000000000000000000000 <
0;
b10000000 :
b1 9
b100000000000000000000000 8
b10000000000000000000000 7
b1111111 6
b100000000000000000000000 5
04
b10000000 3
b100000000000000000000000 2
01
b1000000010000000000000000000000 0
b1000000000000000000000000000000 /
b111111100000000000000000000000 .
bx -
b1000000010000000000000000000000 ,
b101000000000000000000000000000 +
b1000000000000000000000000000000 *
b10111111100000000000000000000000 )
bx (
b1000000000000000000000000000000 '
b111111100000000000000000000000 &
bx %
0$
b1000000000000000000000000000000 #
b111111100000000000000000000000 "
bx !
$end
#1
b0 !
b0 -
1$
#2
b0 %
b0 (
0$
#3
b1000000010000000000000000000000 !
b1000000010000000000000000000000 -
1$
#4
b1 %
b1 (
0$
#5
b10111111100000000000000000000000 !
b10111111100000000000000000000000 -
1$
#6
b10 %
b10 (
0$
#7
b1000000000000000000000000000000 !
b1000000000000000000000000000000 -
1$
#8
b11 %
b11 (
0$
#9
b101000000000000000000000000000 !
b101000000000000000000000000000 -
1$
